aop2db/__init__.py
aop2db/__main__.py
aop2db/aop/__init__.py
aop2db/aop/importer.py
aop2db/aop/query.py
aop2db/aop/utils.py
aop2db/cli.py
aop2db/constants.py
aop2db/defaults.py
aop2db/orm/__init__.py
aop2db/orm/manager.py
aop2db/orm/models.py
aop2db/utils.py
aop2db-0.3.1.dist-info/entry_points.txt
aop2db-0.3.1.dist-info/LICENSE
aop2db-0.3.1.dist-info/WHEEL
aop2db-0.3.1.dist-info/METADATA
aop2db-0.3.1.dist-info/RECORD
