Metadata-Version: 2.1
Name: aop2db
Version: 0.3.1
Summary: AOP2DB - Python parser for converting importing adverse outcome pathway data into a relational database.
Home-page: https://github.com/brucetony/aop2db
License: MIT
Keywords: Biomedical Database
Author: Bruce Schultz
Author-email: bruce.schultz@scai.fraunhofer.de
Maintainer: Bruce Schultz
Maintainer-email: bruce.schultz@scai.fraunhofer.de
Requires-Python: >=3.8,<4.0
Classifier: Development Status :: 5 - Production/Stable
Classifier: Environment :: Console
Classifier: Intended Audience :: Developers
Classifier: Intended Audience :: Science/Research
Classifier: License :: OSI Approved :: MIT License
Classifier: Operating System :: OS Independent
Classifier: Programming Language :: Python
Classifier: Programming Language :: Python :: 3
Classifier: Programming Language :: Python :: 3 :: Only
Classifier: Programming Language :: Python :: 3.10
Classifier: Programming Language :: Python :: 3.8
Classifier: Programming Language :: Python :: 3.9
Classifier: Topic :: Scientific/Engineering :: Bio-Informatics
Requires-Dist: Click (>=8.0,<9.0)
Requires-Dist: cryptography (>=35.0.0,<36.0.0)
Requires-Dist: lxml (>=4.6.5,<5.0.0)
Requires-Dist: pandas (>=1.3.1,<2.0.0)
Requires-Dist: pymysql (>=1.0.2,<2.0.0)
Requires-Dist: requests (>=2.26.0,<3.0.0)
Requires-Dist: sqlalchemy (>=1.4.22,<2.0.0)
Requires-Dist: sqlalchemy_utils (>=0.37.8,<0.38.0)
Requires-Dist: tqdm (>=4.62.0,<5.0.0)
Requires-Dist: xmltodict (==0.12.0)
Project-URL: Documentation, https://aop2db.readthedocs.io/en/latest/
Project-URL: Issue Tracker, https://github.com/brucetony/aop2db/issues
Project-URL: Source Code, https://github.com/brucetony/aop2db
